{
    "version": "0.5.3",
    "description": "Everywhere",
    "homepage": "https://getsharex.com/",
    "license": "Apache License 2.0",
    "url": "https://github.com/DearVa/Everywhere/releases/download/v0.5.3/Everywhere-Windows-x64-v0.5.3.zip",
    "hash": "0a01531d4e99c1445def1e2d757496880c8852ece4c724da9e3e13e54562f272",
    "bin": "Everywhere.Windows.exe",
    "shortcuts": [
        [
            "Everywhere.Windows.exe",
            "Everywhere"
        ]
    ],
    "persist": [
        "settings.ini",
        "Everywhere"
    ],
    "checkver": {
        "github": "https://github.com/DearVa/Everywhere"
    },
    "autoupdate": {
        "url": "https://github.com/DearVa/Everywhere/releases/download/v$version/Everywhere-Windows-x64-v$version.zip"
    }
}
